{
  "اشیاء": [ "چتر", "موبایل", "ساعت", "مداد", "خودکار", "دفتر", "کتاب", "صندلی", "میز", "لیوان", "قاشق", "چنگال", "کاسه", "بشقاب", "کلید", "کیف", "کوله‌پشتی", "کفش", "کلاه", "عینک", "دوربین", "کنترل", "تلویزیون", "یخچال", "ماشین‌لباسشویی", "اتو", "سشوار", "تلفن", "ساعت‌دیوار", "پنکه", "لامپ", "چراغ‌قوه", "نقشه", "خط‌کش", "پاک‌کن", "قیچی", "چسب", "پلاک", "در", "پنجره", "قفل", "آینه", "تابلو", "فرش", "پرده", "بالش", "پتو", "تشک", "زنگ", "ماشین‌حساب", "کامپیوتر", "لپ‌تاپ", "موس", "کیبورد", "پرینتر", "هدفون", "فلش", "باتری", "شمع", "دکمه", "دستکش", "چتر", "پیچ‌گوشتی", "چکش", "اره", "میخ", "آچار", "متر", "کپسول‌گاز", "چراغ‌مطالعه", "دکوری", "ماگ", "بطری‌آب", "قمقمه", "دفترچه", "پایه‌موبایل", "کیف‌پول", "کارت‌بانکی", "پاوربانک", "شارژر", "ماوس‌پد", "میز‌اتوی", "چوب‌لباسی", "دوربین‌مداربسته", "ترازو", "توستر", "آبمیوه‌گیری", "مخلوط‌کن", "قوری", "کتری", "سینی", "قندان", "نمکدان", "جاروبرقی", "جارو", "تی", "سطل", "باسپیکر" ],
  "حیوانات": [ "فیل", "شیر", "ببر", "پلنگ", "خرس", "روباه", "گرگ", "سگ", "گربه", "اسب", "الاغ", "گاو", "گوسفند", "بز", "شتر", "میمون", "کانگورو", "زرافه", "کرگدن", "اسب‌آبی", "لاک‌پشت", "مار", "عقرب", "کروکودیل", "قورباغه", "ماهی", "نهنگ", "دلفین", "کوسه", "خرچنگ", "ستاره‌دریایی", "صدف", "لاک‌پشت‌دریایی", "مرغ", "خروس", "جوجه", "اردک", "غاز", "قو", "بوقلمون", "کبوتر", "کلاغ", "گنجشک", "جغد", "عقاب", "شاهین", "کرکس", "طوطی", "مرغ‌عشق", "سنجاب", "خرگوش", "موش", "جوجه‌تیغی", "خفاش", "کرم", "زنبور", "مگس", "پشه", "مورچه", "سوسک", "کفشدوزک", "عنکبوت", "کرم‌خاکی", "ملخ", "کپک", "گورکن", "راسو", "سمور", "شغال", "کایوت", "تنبل", "خارپشت", "لاما", "کوالا", "پنگوئن", "گراز", "تمساح", "آهو", "گوزن", "شوکا", "خر", "جیرجیرک", "ماهی‌قرمز", "آفتاب‌پرست", "ایگوانا", "جوجه‌اردک", "ماهی‌تن", "ماهی‌کپور", "فیل‌دریایی", "سیل", "خرس‌قطبی", "گرگ‌بیابان", "مرغ‌دریایی", "بلبل", "چکاوک", "دارکوب", "هدهد", "زنبورعسل" ],
  "مکان‌ها": [ "مدرسه", "دانشگاه", "بیمارستان", "کلینیک", "مطب", "کتابخانه", "پارک", "سینما", "تئاتر", "استادیوم", "مسجد", "کلیسا", "کنیسه", "معبد", "رستوران", "کافه", "نانوایی", "سوپرمارکت", "فروشگاه", "پاساژ", "بازار", "میدان", "خیابان", "کوچه", "پل", "تونل", "بزرگراه", "پارکینگ", "فرودگاه", "ایستگاه‌قطار", "ایستگاه‌اتوبوس", "مترو", "ترمینال", "بانک", "پست", "اداره", "دفترکار", "کارخانه", "کارگاه", "آزمایشگاه", "داروخانه", "سالن‌ورزشی", "باشگاه", "استخر", "سالن‌زیبایی", "آرایشگاه", "کتاب‌فروشی", "عکاسی", "پمپ‌بنزین", "کارواش", "باغ", "باغ‌وحش", "مزرعه", "جنگل", "کوه", "دریا", "رودخانه", "دریاچه", "جزیره", "ساحل", "کویر", "بیابان", "یخچال‌طبیعی", "غار", "چشمه", "آبشار", "روستا", "شهر", "استان", "کشور", "قاره", "مرز", "پادگان", "کلانتری", "دادگاه", "زندان", "سفارتخانه", "دفترپلیس", "هتل", "مهمانسرا", "مهمانخانه", "ویلای‌تفریحی", "خانه", "آپارتمان", "اتاق", "آشپزخانه", "حمام", "سرویس‌بهداشتی", "بالکن", "زیرزمین", "انباری", "سقف", "حیاط", "مدرسه‌رانندگی", "آژانس‌مسافرتی", "فرودگاه‌نظامی", "ایستگاه‌فضایی" ],
  "شخصیت‌های معروف": [ "مولوی", "سعدی", "حافظ", "فردوسی", "خیام", "ابن‌سینا", "رازی", "ابوریحان", "نظامی", "عطار", "کوروش‌کبیر", "داریوش", "سهراب‌سپهری", "نیما‌یوشیج", "شاملو", "هوشنگ‌ابتهاج", "احمد‌محمود", "صادق‌هدایت", "جلال‌آل‌احمد", "سیمین‌دانشور", "انیشتین", "نیوتن", "گالیله", "داروین", "ادیسون", "تسلا", "الکساندر‌گراهام‌بل", "مارک‌زاکربرگ", "بیل‌گیتس", "استیو‌جابز", "الون‌ماسک", "نلسون‌ماندلا", "گاندی", "چگوارا", "مادرترزا", "مارتین‌لوتر‌کینگ", "لئوناردو‌داوینچی", "پیکاسو", "ون‌گوگ", "بتهوون", "باخ", "موزارت", "مایکل‌جکسون", "فردی‌مرکوری", "امینم", "بیلی‌آیلیش", "آدله", "ریحانا", "سلنا‌گومز", "کریستیانو‌رونالدو", "لیونل‌مسی", "زین‌الدین‌زیدان", "پله", "مارادونا", "محمد‌صلاح", "کریم‌بنزما", "کی‌روش", "علی‌دایی", "علی‌کریمی", "مهدی‌طارمی", "حسین‌رضازاده", "هادی‌ساعی", "ناصر‌حجازی", "احمدرضا‌عابدزاده", "ابراهیم‌حاتمی‌کیا", "اصغر‌فرهادی", "مجید‌مجیدی", "رضا‌کیانیان", "پرویز‌پرستویی", "شهاب‌حسینی", "نوید‌محمدزاده", "ترانه‌علیدوستی", "مهناز‌افشار", "الیزابت‌دوم", "شاه‌چارلز", "باراک‌اوباما", "جو‌بایدن", "ترامپ", "پوتین", "زلنسکی", "آنگلا‌مرکل", "ماکرون", "اردوغان", "نتانیاهو", "کیم‌جونگ‌اون", "رهبر‌ایران", "رائفی‌پور", "مطهری", "شهید‌سلیمانی", "شهید‌همت", "شهید‌باکری", "بودا" ],
  "مفاهیم": [ "عشق", "آزادی", "زمان", "صدا", "نور", "خواب", "مرگ", "زندگی", "امید", "ترس", "شجاعت", "آرامش", "خشم", "نفرت", "حسادت", "اعتماد", "دوستی", "خیانت", "دانش", "آگاهی", "خنده", "گریه", "حافظه", "تفکر", "هوش", "احساس", "منطق", "روح", "وجدان", "عدالت", "ظلم", "مهربانی", "سعادت", "شکست", "موفقیت", "ثروت", "فقر", "غرور", "تواضع", "افتخار", "خودخواهی", "تجربه", "آینده", "گذشته", "حال", "سرنوشت", "تقدیر", "شانس", "پیشرفت", "پسرفت", "ترقی", "نابودی", "ابدیت", "محدودیت", "بی‌نهایت", "مسئولیت", "وجدان", "فداکاری", "دلسوزی", "همدردی", "حماقت", "پشیمانی", "احترام", "تحقیر", "آزمایش", "امتحان", "قضاوت", "وجدان‌جمعی", "قانون", "آیین", "دین", "ایمان", "کفر", "معجزه", "الهام", "تصور", "تخیل", "واقعیت", "توهم", "عادت", "نیاز", "عشق‌مادر", "عشق‌الهی", "شناخت", "فهم", "تجزیه", "ترکیب", "نیرو", "جرم", "ماده", "انرژی", "حرکت", "سکون", "تغییر", "پایداری", "نظم", "هرج‌ومرج", "زیبایی", "زشتی", "اخلاق", "انصاف", "مسئولیت‌پذیری" ],
  "غذاها": [ "قرمه‌سبزی", "قیمه", "آبگوشت", "کباب", "جوجه‌کباب", "زرشک‌پلو", "عدس‌پلو", "لوبیاپلو", "باقالی‌پلو", "سبزی‌پلو", "ماکارونی", "الویه", "کشک‌بادمجان", "میرزاقاسمی", "کوکو‌سبزی", "کوکو‌سیب‌زمینی", "دلمه", "کتلت", "کوفته", "اشکنه", "اش‌رشته", "اش‌دوغ", "سوپ‌جو", "سوپ‌مرغ", "سوپ‌قارچ", "پیتزا", "همبرگر", "هات‌داگ", "ساندویچ", "فلافل", "شنیتسل", "خوراک‌لوبیا", "خوراک‌دل‌جگر", "خوراک‌عدسی", "تاکو", "ناچو", "چلو‌کباب", "ته‌چین", "خورش‌کرفس", "خورش‌بادمجان", "خورش‌کنگر", "خورش‌قورمه", "خورش‌کدو", "املت", "نیمرو", "صبحانه‌فرنگی", "پنکیک", "فرنی", "شله‌زرد", "حلیم", "حریره", "رشته‌خشکار", "برگر‌گیاهی", "پاستا‌پنه", "پاستا‌فوسیلی", "پاستا‌اسپاگتی", "سس‌پستو", "سس‌آلفردو", "سالاد‌شیرازی", "سالاد‌فصل", "سالاد‌سزار", "ژله", "بستنی", "کیک‌اسفنجی", "کیک‌شکلاتی", "کیک‌هویج", "کاپ‌کیک", "رولت", "پودینگ", "کرپ", "شیرینی‌دانمارکی", "شیرینی‌نخودچی", "کلوچه", "قطاب", "سوهان", "گز", "پشمک", "لواشک", "چیپس", "پفک", "بیسکوییت", "ویفر", "کرم‌کارامل", "چای", "قهوه", "نسکافه", "لاته", "کاپوچینو", "آب‌پرتقال", "آب‌هویج", "شیرموز", "شربت‌به‌لیمو", "شربت‌سکنجبین", "دوغ", "نوشابه", "دلستر", "آب‌معدنی", "آب‌میوه" ],
  "وسایل نقلیه": [ "ماشین", "اتوبوس", "مینی‌بوس", "کامیون", "تریلی", "وانت", "تاکسی", "موتورسیکلت", "دوچرخه", "سه‌چرخه", "اسکوتر", "اسکیت‌برد", "اسکوتر‌برقی", "اتومبیل‌برقی", "ماشین‌سواری", "خودروی‌آفرود", "ماشین‌فرمول‌یک", "ماشین‌پلیس", "ماشین‌آتش‌نشانی", "آمبولانس", "کامیون‌حمل‌زباله", "بولدوزر", "لودر", "بیل‌مکانیکی", "گریدر", "غلتک", "جرثقیل", "قطار", "مترو", "تراموا", "واگن‌باری", "قطار‌سریع‌السیر", "هواپیما", "هلیکوپتر", "گلایدر", "جت", "بالن", "کشتی", "قایق", "قایق‌موتوری", "قایق‌پاروئی", "زیر‌دریایی", "لنج", "یخ‌شکن", "جت‌اسکی", "تراکتور", "کمباین", "ماشین‌چمن‌زن", "اسنوموبیل", "کالسکه", "درشکه", "اسب‌سواری", "شتر‌سواری", "دوچرخه‌برقی", "اتوبوس‌دو‌طبقه", "ماشین‌باری", "کاروان", "تریلر", "ون", "پیکاپ", "اتومبیل‌قدیمی", "ماشین‌عروس", "وانت‌بار", "ماشین‌اجاره‌ای", "ماشین‌لوکس", "شاتل‌فضایی", "کپسول‌فضایی", "پهپاد", "هواپیمای‌بدون‌سرنشین", "قایق‌نجات", "قایق‌چوبی", "قایق‌صیادی", "کشتی‌کروز", "کشتی‌نظامی", "کشتی‌باری", "تاکسی‌هوایی", "ماشین‌گلف", "سگ‌کش", "موتور‌کراس", "موتور‌برقی", "هاوربرد", "وسیله‌نقلیه‌هیبریدی", "اتوبوس‌برقی", "واگن‌مسافری", "واگن‌خواب", "قطارشهری", "راکت‌فضایی", "مونوریل", "هواناو", "ماشین‌خودران", "ماشین‌بازی", "دوچرخه‌کوهستان", "دوچرخه‌شهری", "موتور‌سنگین", "جت‌خصوصی" ],
  "مشاغل": [ "پزشک", "پرستار", "دندانپزشک", "داروساز", "دامپزشک", "جراح", "روانپزشک", "روانشناس", "معلم", "استاددانشگاه", "مدیر", "کارمند", "برنامه‌نویس", "مهندس‌نرم‌افزار", "مهندس‌عمران", "مهندس‌مکانیک", "مهندس‌برق", "مهندس‌معماری", "راننده", "آتش‌نشان", "پلیس", "سرباز", "قاضی", "وکیل", "کارگر", "نجار", "آهنگر", "جوشکار", "برق‌کار", "تاسیساتی", "لوله‌کش", "مکانیک", "نقاش‌ساختمان", "کاشیکار", "معمار", "کفاش", "خیاط", "طراح‌لباس", "آرایشگر", "عکاس", "فیلمبردار", "بازیگر", "کارگردان", "فیلمنامه‌نویس", "نویسنده", "شاعر", "مترجم", "خبرنگار", "مجری", "گوینده", "موزیسین", "نوازنده", "خواننده", "آهنگساز", "نقاش", "طراح‌گرافیک", "انیماتور", "تدوین‌گر", "مدیررسانه", "بازاریاب", "فروشنده", "کاسب", "صندوقدار", "راننده‌تاکسی", "راننده‌اتوبوس", "پیک", "تحویل‌دار", "نظافتچی", "نگهبان", "کارشناس‌کامپیوتر", "کارشناس‌مالی", "حسابدار", "صراف", "بانکدار", "تحلیلگر", "معامله‌گر‌بورس", "مربی‌ورزشی", "ورزشکار", "مربی‌یوگا", "داور", "آشپز", "شیرینی‌پز", "نانوا", "قناد", "پیک‌موتوری", "کشاورز", "دامدار", "باغبان", "ماهیگیر", "پستچی", "مهماندار‌هواپیما", "خلبان", "کنترلر‌پرواز", "دریادار", "افسر", "روحانی", "امام‌جمعه", "سخنران" ],
  "تکنولوژی ": [ "کامپیوتر", "موبایل", "تبلت", "لپ‌تاپ", "تلویزیون", "کنسول‌بازی", "پلی‌استیشن", "ایکس‌باکس", "نینتندو", "هدفون", "بلوتوث", "وای‌فای", "اینترنت", "مودم", "روتر", "پاوربانک", "شارژر", "هارد‌اکسترنال", "فلش", "پردازنده", "کارت‌گرافیک", "رم", "پرینتر", "اسکنر", "دوربین", "دوربین‌مداربسته", "وب‌کم", "ساعت‌هوشمند", "عینک‌واقعیت‌مجازی", "واقعیت‌افزوده", "ربات", "روبات‌خدمتکار", "هوش‌مصنوعی", "چت‌بات", "پلتفرم", "اپلیکیشن", "نرم‌افزار", "سیستم‌عامل", "ویندوز", "مک‌اواس", "اندروید", "لینوکس", "سرور", "هاست", "کلاود", "دیتاسنتر", "رمزارز", "بلاکچین", "چاپگر‌سه‌بعدی", "لیزر", "اسکنر‌اثر‌انگشت", "تشخیص‌چهره", "ماشین‌خودران", "پهپاد", "شاتل‌فضایی", "تلسکوپ", "ماهواره", "نقشه‌آنلاین", "پلتفرم‌پرداخت", "درگاه‌پرداخت", "رمز‌پویا", "کیوآر‌کد", "تیک‌تاک", "اینستاگرام", "فیسبوک", "یوتیوب", "گوگل", "بینگ", "چت‌جی‌پی‌تی", "دیتابیس", "SQL", "کدنویسی", "برنامه‌نویسی", "پایتون", "ری‌اکت", "نود", "روبات‌صنعتی", "ماشین‌هوشمند", "سنسور", "اینترنت‌اشیا", "هوشمندسازی", "خانه‌هوشمند", "ساعت‌هوشمند", "واقعیت‌مجازی", "هدست‌واقعیت‌مجازی", "اسکن‌سه‌بعدی", "هوش‌مصنوعی‌مولد", "زبان‌مدل", "چت‌بات‌های‌پیشرفته" ]
}

